embcol/__init__.py
embcol/_checking.py
embcol/_exception.py
embcol/_repr.py
embcol/_typing_imports.py
embcol/_utils.py
embcol/py.typed
embcol/random.py
embcol/typing.py
embcol/color/__init__.py
embcol/color/_conversions.py
embcol/color/_difference.py
embcol/color/_mapping.py
embcol/color/_wrappers.py
embcol/logging/__init__.py
embcol/logging/_context.py
embcol/logging/_figure.py
embcol/logging/_message.py
embcol/optimizers/__init__.py
embcol/optimizers/_base.py
embcol/optimizers/_cmaes.py
embcol/optimizers/_de.py
embcol/optimizers/_random.py
embcol/optimizers/_slsqp.py
embcol/optimizers/_trustregion.py
embcol/problem/__init__.py
embcol/problem/_bounds.py
embcol/problem/_constraints.py
embcol/problem/_problem.py
embcol-0.1.0.dist-info/licenses/LICENSE.txt
embcol-0.1.0.dist-info/METADATA
embcol-0.1.0.dist-info/WHEEL
embcol-0.1.0.dist-info/top_level.txt
embcol-0.1.0.dist-info/RECORD
